karrio/mappers/nationex/__init__.py
karrio/mappers/nationex/mapper.py
karrio/mappers/nationex/proxy.py
karrio/mappers/nationex/settings.py
karrio/plugins/nationex/__init__.py
karrio/providers/nationex/__init__.py
karrio/providers/nationex/error.py
karrio/providers/nationex/rate.py
karrio/providers/nationex/tracking.py
karrio/providers/nationex/units.py
karrio/providers/nationex/utils.py
karrio/providers/nationex/shipment/__init__.py
karrio/providers/nationex/shipment/cancel.py
karrio/providers/nationex/shipment/create.py
karrio/schemas/nationex/__init__.py
karrio/schemas/nationex/error.py
karrio/schemas/nationex/rate_request.py
karrio/schemas/nationex/rate_response.py
karrio/schemas/nationex/shipment_request.py
karrio/schemas/nationex/shipment_response.py
karrio/schemas/nationex/tracking_response.py
karrio_nationex-2026.1.4.dist-info/METADATA
karrio_nationex-2026.1.4.dist-info/WHEEL
karrio_nationex-2026.1.4.dist-info/entry_points.txt
karrio_nationex-2026.1.4.dist-info/top_level.txt
karrio_nationex-2026.1.4.dist-info/RECORD
